gitlinks/__init__.py
gitlinks/cli.py
gitlinks/utils.py
gitlinks-0.2.dist-info/LICENSE
gitlinks-0.2.dist-info/METADATA
gitlinks-0.2.dist-info/WHEEL
gitlinks-0.2.dist-info/entry_points.txt
gitlinks-0.2.dist-info/top_level.txt
gitlinks-0.2.dist-info/RECORD
