Metadata-Version: 2.1
Name: gitlinks
Version: 0.2
Summary: GitHub pages-powered shortlinks.
Home-page: https://github.com/lengstrom/gitlinks
Author: Logan Engstrom
Author-email: logan@mit.edu
License: UNKNOWN
Platform: UNKNOWN
Classifier: Programming Language :: Python :: 3
Classifier: License :: OSI Approved :: GNU General Public License v3 (GPLv3)
Classifier: Operating System :: OS Independent
Classifier: Development Status :: 4 - Beta
Classifier: Environment :: Console
Requires-Python: >=3.6
Requires-Dist: docopt (>=0.6.2)
Requires-Dist: GitPython (>=3.1.13)
Requires-Dist: ilock (>=1.0.3)
Requires-Dist: pandas (>=1.2.2)
Requires-Dist: portalocker (>=2.2.1)
Requires-Dist: requests (>=2.25.1)
Requires-Dist: requests-toolbelt (>=0.9.1)
Requires-Dist: tabulate (>=0.8.9)
Requires-Dist: tqdm (>=4.58.0)
